qa_testing_utils/__init__.py
qa_testing_utils/exception_utils.py
qa_testing_utils/exceptions.py
qa_testing_utils/file_utils.py
qa_testing_utils/logger.py
qa_testing_utils/matchers.py
qa_testing_utils/object_utils.py
qa_testing_utils/stream_utils.py
qa_testing_utils/string_utils.py
qa_testing_utils/thread_utils.py
qa_testing_utils/tuple_utils.py
qa_testing_utils-0.1.1.dist-info/METADATA
qa_testing_utils-0.1.1.dist-info/WHEEL
qa_testing_utils-0.1.1.dist-info/RECORD
